setup.py
Ocspy/__init__.py
Ocspy/utilities.py
Ocspy/Base/SignalInterface.py
Ocspy/Base/__init__.py
Ocspy/Channel/__init__.py
Ocspy/Channel/channel.py
Ocspy/Channel/ssfm.py
Ocspy/Filter/__init__.py
Ocspy/Filter/designFilter.py
Ocspy/Instrument/ElectricInstrument.py
Ocspy/Instrument/OpticalInstrument.py
Ocspy/Instrument/__init__.py
Ocspy/ReceiverDsp/__init__.py
Ocspy/ReceiverDsp/dsp_tools.py
Ocspy/ReceiverDsp/receiver.py
Ocspy/ReceiverDsp/receiver_dsp.py
Ocspy/ReceiverDsp/receiver_metrics.py
Ocspy/qamdata/16qam.py
Ocspy/qamdata/32qam.py
Ocspy/qamdata/4qam.py
Ocspy/qamdata/64qam.py
Ocspy/qamdata/8qam.py
Ocspy/qamdata/__init__.py
Ocspy/tool/__init__.py
Ocspy/tool/tool.py
ocspy.egg-info/PKG-INFO
ocspy.egg-info/SOURCES.txt
ocspy.egg-info/dependency_links.txt
ocspy.egg-info/requires.txt
ocspy.egg-info/top_level.txt