Metadata-Version: 1.0
Name: ocspy
Version: 0.4.7
Summary: simulate optical communication
Home-page: UNKNOWN
Author: nigulasikaochuan
Author-email: nigulasikaochuan@sjtu.edu.cn
License: MIT Licence
Keywords: pip,optical communication,coherent optical,ocspy,ocspy
Platform: any
